cli/__init__.py
cli/arguments.py
cli/custom_argparse.py
cli/help.py
cli/imports.py
cli/logging.py
cli/main.py
cli/model_candidate.py
cli/model_creator.py
cli/model_field.py
cli/model_info.py
cli/process_files.py
cli/utils.py
cli/cache/__init__.py
cli/containers/__init__.py
cli/containers/get_creators.py
cli/containers/masked_files_container.py
cli/containers/metadata_folder_container.py
cli/containers/metadata_xlsx_container.py
cli/containers/unique_file_container.py
cli/create_files/__init__.py
cli/create_files/create_dto.py
cli/create_files/create_files.py
cli/create_files/create_init.py
cli/create_files/create_ms_json.py
cli/create_files/create_ms_model.py
cli/create_files/create_promax_json.py
cli/create_files/create_promax_model.py
cli/create_files/file_output.py
cli/create_files/process_files.py
cli/data_type/__init__.py
cli/data_type/complex_types.py
cli/data_type/primitive_types.py
cli/interfaces/__init__.py
cli/interfaces/metadata_container_interface.py
cli/tools/__init__.py
canaa_model_furlan-0.2.0.dist-info/METADATA
canaa_model_furlan-0.2.0.dist-info/WHEEL
canaa_model_furlan-0.2.0.dist-info/entry_points.txt
canaa_model_furlan-0.2.0.dist-info/top_level.txt
canaa_model_furlan-0.2.0.dist-info/RECORD
