Metadata-Version: 2.1
Name: canaa-model-furlan
Version: 0.2.0
Summary: Canaa model creator
Home-page: https://github.com/guionardo/canaa-base-model-creator
Author: Guionardo Furlan
Author-email: guionardo.furlan@hbsis.com.br
License: MIT
Project-URL: Documentation, https://github.com/guionardo/canaa-base-model-creator/wiki
Project-URL: Source, https://github.com/guionardo/canaa-base-model-creator
Keywords: canaa hbsis
Platform: UNKNOWN
Classifier: Development Status :: 4 - Beta
Classifier: Environment :: Console
Classifier: Intended Audience :: Developers
Classifier: License :: OSI Approved :: MIT License
Classifier: Topic :: Software Development :: Build Tools
Classifier: Topic :: Utilities
Classifier: Programming Language :: Python
Classifier: Programming Language :: Python :: 3.6
Classifier: Programming Language :: Python :: 3.7
Classifier: Programming Language :: Python :: 3.8
Requires-Python: >=3.6.*
Requires-Dist: Faker
Requires-Dist: openpyxl
